pentools/__init__.py
pentools/__main__.py
pentools/cli.py
pentools/client.py
pentools/responses.py
pentools/settings.py
pentools/commands/__init__.py
pentools/commands/list.py
pentools/commands/script.py
pentools/types/__init__.py
pentools/types/exceptions.py
pentools/types/resource.py
pentools/types/response.py
pentools/types/settings.py
pentools-0.0.1.dist-info/METADATA
pentools-0.0.1.dist-info/WHEEL
pentools-0.0.1.dist-info/entry_points.txt
pentools-0.0.1.dist-info/top_level.txt
pentools-0.0.1.dist-info/RECORD
